{
  "title": "Low Sodium Honey Mustard Sauce",
  "ingredients": [
    "3/4 cup Greek nonfat yogurt (ex. Chobani)",
    "1/4 cup honey",
    "1 tbs white distilled vinegar",
    "1 tbs ground mustard powder",
    "1/4 tsp garlic powder",
    "1/4 tsp onion powder",
    "1/4 tsp turmeric"
  ],
  "directions": [
    "Mix ground mustard powder with distilled vinegar in bowl and stir well.",
    "Add garlic powder, onion powder and tumeric and stir until combined.",
    "Mix in Greek yogurt and then add honey. Stir well.",
    "Refrigerate any leftovers for one week after use."
  ],
  "photo": "/photos/Low Sodium Honey Mustard Sauce.jpg",
  "tags": [
    "condiment",
    "low sodium"
  ]
}
